trust_patern_full_ex_sar_forex_next3
