Metadata-Version: 1.0
Name: trust-patern-full-ex-sar-forex-next3
Version: 2.5
Summary: trust_patern_full_ex_sar_forex_next3
Home-page: UNKNOWN
Author: omid
Author-email: UNKNOWN
License: UNKNOWN
Platform: UNKNOWN
